{
    "schema_version": "v1",
    "name_for_model": "MathPlugin",
    "name_for_human": "Math Plugin",
    "description_for_model": "A plugin that does math operations.",
    "description_for_human": "A plugin that does math operations.",
    "auth": {
        "type": "none",
        "authorization_url": ""
    },
    "api": {
        "type": "openapi",
        "url": "https://team4functionapppsaitech.azurewebsites.net:443/swagger.json",
        "has_user_authentication": false
    },
    "logo_url": "https://team4functionapppsaitech.azurewebsites.net:443/logo.jpeg",
    "contact_email": "keetu.jk@gmail.com",
    "legal_info_url": "http://www.example.com/legal"
}
